terminalle/__init__.py
terminalle/__main__.py
terminalle/auto.py
terminalle/key.py
terminalle/party.will.Terminalle.service
terminalle/settings.py
terminalle/terminalle.desktop
terminalle/terminalle.py
terminalle-2.0.0.data/data/share/man/man1/terminalle.1
terminalle-2.0.0.dist-info/licenses/LICENSE.md
terminalle-2.0.0.dist-info/METADATA
terminalle-2.0.0.dist-info/WHEEL
terminalle-2.0.0.dist-info/entry_points.txt
terminalle-2.0.0.dist-info/top_level.txt
terminalle-2.0.0.dist-info/RECORD
