Metadata-Version: 2.4
Name: terminalle
Version: 2.0.0
Summary: A fancy drop-down terminal emulateur.
Author-email: Will Noble <author@will.party>
License-Expression: MIT-0
Project-URL: Repository, https://github.com/will/terminalle
Keywords: terminal,emulator,drop-down,freedesktop,gdk,gtk,gnome,vte,console,sick
Classifier: Intended Audience :: End Users/Desktop
Classifier: Topic :: Desktop Environment
Classifier: Topic :: Terminals
Requires-Python: >=3.12
License-File: LICENSE.md
Requires-Dist: PyGObject>=3.42.2
Requires-Dist: PyYAML>=6.0
Dynamic: license-file
